keras_edge/__init__.py
keras_edge/converters/__init__.py
keras_edge/converters/cpp/__init__.py
keras_edge/converters/cpp/utils.py
keras_edge/converters/tflite/__init__.py
keras_edge/converters/tflite/converter.py
keras_edge/converters/torch/__init__.py
keras_edge/dataloaders/__init__.py
keras_edge/interpreters/__init__.py
keras_edge/interpreters/tflite.py
keras_edge/layers/__init__.py
keras_edge/layers/patching.py
keras_edge/layers/preprocessing/__init__.py
keras_edge/layers/preprocessing/audio/__init__.py
keras_edge/layers/preprocessing/audio/specaugment.py
keras_edge/layers/preprocessing/ts/__init__.py
keras_edge/layers/preprocessing/vision/__init__.py
keras_edge/metrics/__init__.py
keras_edge/metrics/flops.py
keras_edge/metrics/threshold.py
keras_edge/models/__init__.py
keras_edge/models/activations.py
keras_edge/models/blocks.py
keras_edge/models/cct.py
keras_edge/models/composer.py
keras_edge/models/conformer.py
keras_edge/models/convmixer.py
keras_edge/models/defines.py
keras_edge/models/efficientnet.py
keras_edge/models/metaformer.py
keras_edge/models/mobilenet.py
keras_edge/models/mobileone.py
keras_edge/models/optimizers/__init__.py
keras_edge/models/optimizers/contrastive.py
keras_edge/models/optimizers/distiller.py
keras_edge/models/optimizers/maskautoencoder.py
keras_edge/models/optimizers/simclr.py
keras_edge/models/regnet.py
keras_edge/models/resnet.py
keras_edge/models/tcn.py
keras_edge/models/tsmixer.py
keras_edge/models/unet.py
keras_edge/models/unext.py
keras_edge/models/utils.py
keras_edge/plotting/__init__.py
keras_edge/plotting/cm.py
keras_edge/plotting/roc.py
keras_edge/quantizers/__init__.py
keras_edge/utils.py
keras_edge-0.1.2.dist-info/LICENSE
keras_edge-0.1.2.dist-info/METADATA
keras_edge-0.1.2.dist-info/WHEEL
keras_edge-0.1.2.dist-info/RECORD
