Metadata-Version: 2.1
Name: keras-edge
Version: 0.1.2
Summary: 
Author: Ambiq AI
Author-email: support.aitg@ambiq.com
Requires-Python: >=3.11,<3.13
Classifier: Programming Language :: Python :: 3
Classifier: Programming Language :: Python :: 3.11
Classifier: Programming Language :: Python :: 3.12
Requires-Dist: h5py (>=3.10.0,<4.0.0)
Requires-Dist: keras (>=3.0.4,<4.0.0)
Requires-Dist: matplotlib (>=3.9.0,<4.0.0)
Requires-Dist: pandas (>=2.2.2,<3.0.0)
Requires-Dist: plotly (>=5.22.0,<6.0.0)
Requires-Dist: pydantic (>=2.6.1,<3.0.0)
Requires-Dist: requests (>=2.31.0,<3.0.0)
Requires-Dist: scikit-learn (>=1.5.1,<2.0.0)
Requires-Dist: seaborn (>=0.13.2,<0.14.0)
Requires-Dist: tensorflow (>=2.16.1,<3.0.0)
Requires-Dist: tqdm (>=4.66.4,<5.0.0)
